gifconvert_basic_tomas/__init__.py
gifconvert_basic_tomas/pngtogif.py
gifconvert_basic_tomas-1.0.2.dist-info/LICENSE
gifconvert_basic_tomas-1.0.2.dist-info/METADATA
gifconvert_basic_tomas-1.0.2.dist-info/WHEEL
gifconvert_basic_tomas-1.0.2.dist-info/top_level.txt
gifconvert_basic_tomas-1.0.2.dist-info/RECORD
